{
  "_class": "group",
  "booleanOperation": -1,
  "clippingMaskMode": 0,
  "do_objectID": "DEABCAAF-C9EB-47E1-8F8A-9D9E5AA6514E",
  "exportOptions": {
    "_class": "exportOptions",
    "exportFormats": [
    ],
    "includedLayerIds": [
    ],
    "layerOptions": 0,
    "shouldTrim": false
  },
  "frame": {
    "_class": "rect",
    "constrainProportions": false,
    "height": 42,
    "width": 52,
    "x": 1327,
    "y": 26
  },
  "groupLayout": {
    "_class": "MSImmutableFreeformGroupLayout"
  },
  "hasClickThrough": false,
  "hasClippingMask": false,
  "isFixedToViewport": false,
  "isFlippedHorizontal": false,
  "isFlippedVertical": false,
  "isLocked": false,
  "isVisible": true,
  "layerListExpandedType": 0,
  "layers": [
    {
      "class": "shapePath",
      "id": "D16062CB-2F95-434A-8B72-CB0183CBE33F"
    },
    {
      "class": "shapePath",
      "id": "B7AFE509-D8DF-43D8-8140-7F68908EDD41"
    },
    {
      "class": "shapePath",
      "id": "1CF7DB19-83CE-4188-A133-90AE4ABA1E80"
    },
    {
      "class": "oval",
      "id": "9CD4F53F-FD69-465E-A950-1D457A33FCA4"
    },
    {
      "class": "oval",
      "id": "2A224D4D-9A17-4589-B848-367492B8C3E0"
    },
    {
      "class": "oval",
      "id": "7ED15136-0013-4FDE-B41E-AEB1972C7B29"
    },
    {
      "class": "text",
      "id": "4BC5280A-EC2D-492B-98BA-965F4815C3E5"
    }
  ],
  "name": "Shopping Cart",
  "nameIsFixed": false,
  "resizingConstraint": 63,
  "resizingType": 0,
  "rotation": 0,
  "shouldBreakMaskChain": false,
  "style": {
    "_class": "style",
    "blur": {
      "_class": "blur",
      "center": "{0.5, 0.5}",
      "isEnabled": false,
      "motionAngle": 0,
      "radius": 13.68421052631579,
      "saturation": 1,
      "type": 0
    },
    "borderOptions": {
      "_class": "borderOptions",
      "dashPattern": [
      ],
      "isEnabled": true,
      "lineCapStyle": 0,
      "lineJoinStyle": 0
    },
    "borders": [
    ],
    "colorControls": {
      "_class": "colorControls",
      "brightness": 0,
      "contrast": 1,
      "hue": 0,
      "isEnabled": false,
      "saturation": 1
    },
    "contextSettings": {
      "_class": "graphicsContextSettings",
      "blendMode": 0,
      "opacity": 1
    },
    "do_objectID": "CCA49663-B099-4E34-B544-C31781704BCE",
    "endMarkerType": 0,
    "fills": [
    ],
    "innerShadows": [
    ],
    "miterLimit": 10,
    "shadows": [
    ],
    "startMarkerType": 0,
    "windingRule": 1
  }
}